{
    "total": [
        {
            "id": "100068096370437",
            "count": 2
        },
        {
            "id": "100060771549247",
            "count": 0
        },
        {
            "id": "100093788380191",
            "count": 0
        },
        {
            "id": "61551902034746",
            "count": 0
        },
        {
            "id": "100089516232276",
            "count": 0
        },
        {
            "id": "1631016269",
            "count": 0
        },
        {
            "id": "100055154154050",
            "count": 11
        },
        {
            "id": "1270787329",
            "count": 0
        },
        {
            "id": "61556835487566",
            "count": 0
        },
        {
            "id": "61557610827776",
            "count": 0
        },
        {
            "id": "61560874059259",
            "count": 0
        },
        {
            "id": "61560876910939",
            "count": 0
        },
        {
            "id": "61552931911306",
            "count": 0
        },
        {
            "id": "61561087751392",
            "count": 5
        },
        {
            "id": "61561409300932",
            "count": 6
        },
        {
            "id": "61561789973188",
            "count": 1
        }
    ],
    "week": [
        {
            "id": "100068096370437",
            "count": 0,
            "name": "Phạm Minh Đồng"
        },
        {
            "id": "100060771549247",
            "count": 0,
            "name": "The Tran"
        },
        {
            "id": "100093788380191",
            "count": 0,
            "name": "Phạm Quang Vũ"
        },
        {
            "id": "61551902034746",
            "count": 0,
            "name": "Vân Du"
        },
        {
            "id": "100089516232276",
            "count": 0,
            "name": "Tín Phan"
        },
        {
            "id": "1631016269",
            "count": 0,
            "name": "Phạm Minh Đồng"
        },
        {
            "id": "100055154154050",
            "count": 0,
            "name": "Võ N-đăng"
        },
        {
            "id": "1270787329",
            "count": 0,
            "name": "Ngân Quỳnh Hoa"
        },
        {
            "id": "61556835487566",
            "count": 0,
            "name": "Quốc Tuấn"
        },
        {
            "id": "61557610827776",
            "count": 0,
            "name": "Đào Ngọc"
        },
        {
            "id": "61560874059259",
            "count": 0,
            "name": "Yến Nhi"
        },
        {
            "id": "61560876910939",
            "count": 0,
            "name": "Nguyễn V-Trung"
        },
        {
            "id": "61552931911306",
            "count": 0,
            "name": "Chigiri Hyoma"
        },
        {
            "id": "61561087751392",
            "count": 0,
            "name": "Puppi Candy"
        },
        {
            "id": "61561409300932",
            "count": 0,
            "name": "Nhật Đăng"
        },
        {
            "id": "61561789973188",
            "count": 0,
            "name": "Chi Uyên"
        }
    ],
    "day": [
        {
            "id": "100068096370437",
            "count": 0,
            "name": "Phạm Minh Đồng"
        },
        {
            "id": "100060771549247",
            "count": 0,
            "name": "The Tran"
        },
        {
            "id": "100093788380191",
            "count": 0,
            "name": "Phạm Quang Vũ"
        },
        {
            "id": "61551902034746",
            "count": 0,
            "name": "Vân Du"
        },
        {
            "id": "100089516232276",
            "count": 0,
            "name": "Tín Phan"
        },
        {
            "id": "1631016269",
            "count": 0,
            "name": "Phạm Minh Đồng"
        },
        {
            "id": "100055154154050",
            "count": 0,
            "name": "Võ N-đăng"
        },
        {
            "id": "1270787329",
            "count": 0,
            "name": "Ngân Quỳnh Hoa"
        },
        {
            "id": "61556835487566",
            "count": 0,
            "name": "Quốc Tuấn"
        },
        {
            "id": "61557610827776",
            "count": 0,
            "name": "Đào Ngọc"
        },
        {
            "id": "61560874059259",
            "count": 0,
            "name": "Yến Nhi"
        },
        {
            "id": "61560876910939",
            "count": 0,
            "name": "Nguyễn V-Trung"
        },
        {
            "id": "61552931911306",
            "count": 0,
            "name": "Chigiri Hyoma"
        },
        {
            "id": "61561087751392",
            "count": 0,
            "name": "Puppi Candy"
        },
        {
            "id": "61561409300932",
            "count": 0,
            "name": "Nhật Đăng"
        },
        {
            "id": "61561789973188",
            "count": 0,
            "name": "Chi Uyên"
        }
    ],
    "time": 0,
    "last": {
        "time": 2,
        "day": [
            {
                "id": "100068096370437",
                "count": 0
            },
            {
                "id": "100060771549247",
                "count": 0
            },
            {
                "id": "100093788380191",
                "count": 0
            },
            {
                "id": "61551902034746",
                "count": 0
            },
            {
                "id": "100089516232276",
                "count": 0
            },
            {
                "id": "1631016269",
                "count": 0
            },
            {
                "id": "100055154154050",
                "count": 0
            },
            {
                "id": "100026363505982",
                "count": 0
            },
            {
                "id": "1270787329",
                "count": 0
            },
            {
                "id": "61556835487566",
                "count": 0
            },
            {
                "id": "61557610827776",
                "count": 0
            },
            {
                "id": "61560874059259",
                "count": 0
            },
            {
                "id": "61560876910939",
                "count": 0
            },
            {
                "id": "61552931911306",
                "count": 0
            },
            {
                "id": "61561087751392",
                "count": 0
            },
            {
                "id": "61561409300932",
                "count": 0
            },
            {
                "id": "61561789973188",
                "count": 0
            }
        ],
        "week": [
            {
                "id": "100068096370437",
                "count": 0
            },
            {
                "id": "100060771549247",
                "count": 0
            },
            {
                "id": "100093788380191",
                "count": 0
            },
            {
                "id": "61551902034746",
                "count": 0
            },
            {
                "id": "100089516232276",
                "count": 0
            },
            {
                "id": "1631016269",
                "count": 0
            },
            {
                "id": "100055154154050",
                "count": 0
            },
            {
                "id": "100026363505982",
                "count": 0
            },
            {
                "id": "1270787329",
                "count": 0
            },
            {
                "id": "61556835487566",
                "count": 0
            },
            {
                "id": "61557610827776",
                "count": 0
            },
            {
                "id": "61560874059259",
                "count": 0
            },
            {
                "id": "61560876910939",
                "count": 0
            },
            {
                "id": "61552931911306",
                "count": 0
            },
            {
                "id": "61561087751392",
                "count": 0
            },
            {
                "id": "61561409300932",
                "count": 0
            },
            {
                "id": "61561789973188",
                "count": 0
            }
        ]
    }
}