{
    "total": [
        {
            "id": "61556886926538",
            "count": 0
        },
        {
            "id": "61558838883021",
            "count": 0
        },
        {
            "id": "100076747794030",
            "count": 0
        },
        {
            "id": "100092162366896",
            "count": 0
        },
        {
            "id": "100045313671777",
            "count": 0
        },
        {
            "id": "100094296957853",
            "count": 0
        },
        {
            "id": "100047832720086",
            "count": 0
        },
        {
            "id": "61558759585711",
            "count": 0
        },
        {
            "id": "61558167103810",
            "count": 0
        },
        {
            "id": "100089263542479",
            "count": 0
        },
        {
            "id": "100091885795030",
            "count": 0
        },
        {
            "id": "61559924222307",
            "count": 0
        },
        {
            "id": "100022088556574",
            "count": 0
        },
        {
            "id": "61555802415021",
            "count": 0
        },
        {
            "id": "100072118997942",
            "count": 0
        },
        {
            "id": "61551677327636",
            "count": 0
        },
        {
            "id": "100084451148154",
            "count": 0
        },
        {
            "id": "61555932106977",
            "count": 0
        },
        {
            "id": "61558980782920",
            "count": 0
        },
        {
            "id": "100076986559695",
            "count": 0
        },
        {
            "id": "100062402694808",
            "count": 0
        },
        {
            "id": "61554868495444",
            "count": 0
        },
        {
            "id": "61560526196531",
            "count": 0
        },
        {
            "id": "61557458320499",
            "count": 11
        },
        {
            "id": "61561083304968",
            "count": 0
        },
        {
            "id": "100029609839915",
            "count": 0
        },
        {
            "id": "100080955501166",
            "count": 0
        },
        {
            "id": "61560272435082",
            "count": 0
        },
        {
            "id": "100088522154088",
            "count": 0
        },
        {
            "id": "61557646453984",
            "count": 0
        },
        {
            "id": "100063494506611",
            "count": 0
        },
        {
            "id": "61555275488530",
            "count": 0
        },
        {
            "id": "61559683718272",
            "count": 0
        },
        {
            "id": "61559402953522",
            "count": 0
        },
        {
            "id": "61557543538603",
            "count": 0
        },
        {
            "id": "100090484572893",
            "count": 0
        },
        {
            "id": "61553785805211",
            "count": 0
        },
        {
            "id": "61557564551067",
            "count": 0
        },
        {
            "id": "100074751587160",
            "count": 0
        },
        {
            "id": "61556569884849",
            "count": 0
        },
        {
            "id": "61556541176393",
            "count": 0
        },
        {
            "id": "100066564932411",
            "count": 0
        },
        {
            "id": "100084606307564",
            "count": 0
        },
        {
            "id": "61560935327622",
            "count": 0
        },
        {
            "id": "100089195796584",
            "count": 1
        },
        {
            "id": "61560917451145",
            "count": 0
        },
        {
            "id": "100091887548073",
            "count": 0
        },
        {
            "id": "100059415515587",
            "count": 0
        },
        {
            "id": "100070262270937",
            "count": 0
        },
        {
            "id": "61561027125365",
            "count": 0
        },
        {
            "id": "100055154154050",
            "count": 14
        },
        {
            "id": "100067455634994",
            "count": 0
        },
        {
            "id": "61550042293602",
            "count": 0
        },
        {
            "id": "61561510254962",
            "count": 0
        },
        {
            "id": "61551991460052",
            "count": 1
        }
    ],
    "week": [
        {
            "id": "61556886926538",
            "count": 0
        },
        {
            "id": "61558838883021",
            "count": 0
        },
        {
            "id": "100076747794030",
            "count": 0
        },
        {
            "id": "100092162366896",
            "count": 0
        },
        {
            "id": "100045313671777",
            "count": 0
        },
        {
            "id": "100094296957853",
            "count": 0
        },
        {
            "id": "100047832720086",
            "count": 0
        },
        {
            "id": "61558759585711",
            "count": 0
        },
        {
            "id": "61558167103810",
            "count": 0
        },
        {
            "id": "100089263542479",
            "count": 0
        },
        {
            "id": "100091885795030",
            "count": 0
        },
        {
            "id": "61559924222307",
            "count": 0
        },
        {
            "id": "100022088556574",
            "count": 0
        },
        {
            "id": "61555802415021",
            "count": 0
        },
        {
            "id": "100072118997942",
            "count": 0
        },
        {
            "id": "61551677327636",
            "count": 0
        },
        {
            "id": "100084451148154",
            "count": 0
        },
        {
            "id": "61555932106977",
            "count": 0
        },
        {
            "id": "61558980782920",
            "count": 0
        },
        {
            "id": "100076986559695",
            "count": 0
        },
        {
            "id": "100062402694808",
            "count": 0
        },
        {
            "id": "61554868495444",
            "count": 0
        },
        {
            "id": "61560526196531",
            "count": 0
        },
        {
            "id": "61557458320499",
            "count": 11
        },
        {
            "id": "61561083304968",
            "count": 0
        },
        {
            "id": "100029609839915",
            "count": 0
        },
        {
            "id": "100080955501166",
            "count": 0
        },
        {
            "id": "61560272435082",
            "count": 0
        },
        {
            "id": "100088522154088",
            "count": 0
        },
        {
            "id": "61557646453984",
            "count": 0
        },
        {
            "id": "100063494506611",
            "count": 0
        },
        {
            "id": "61555275488530",
            "count": 0
        },
        {
            "id": "61559683718272",
            "count": 0
        },
        {
            "id": "61559402953522",
            "count": 0
        },
        {
            "id": "61557543538603",
            "count": 0
        },
        {
            "id": "100090484572893",
            "count": 0
        },
        {
            "id": "61553785805211",
            "count": 0
        },
        {
            "id": "61557564551067",
            "count": 0
        },
        {
            "id": "100074751587160",
            "count": 0
        },
        {
            "id": "61556569884849",
            "count": 0
        },
        {
            "id": "61556541176393",
            "count": 0
        },
        {
            "id": "100066564932411",
            "count": 0
        },
        {
            "id": "100084606307564",
            "count": 0
        },
        {
            "id": "61560935327622",
            "count": 0
        },
        {
            "id": "100089195796584",
            "count": 1
        },
        {
            "id": "61560917451145",
            "count": 0
        },
        {
            "id": "100091887548073",
            "count": 0
        },
        {
            "id": "100059415515587",
            "count": 0
        },
        {
            "id": "100070262270937",
            "count": 0
        },
        {
            "id": "61561027125365",
            "count": 0
        },
        {
            "id": "100055154154050",
            "count": 14
        },
        {
            "id": "100067455634994",
            "count": 0
        },
        {
            "id": "61550042293602",
            "count": 0
        },
        {
            "id": "61561510254962",
            "count": 0
        },
        {
            "id": "61551991460052",
            "count": 1
        }
    ],
    "day": [
        {
            "id": "61556886926538",
            "count": 0,
            "name": "Dingg Kool"
        },
        {
            "id": "61558838883021",
            "count": 0,
            "name": "Khánh Băng"
        },
        {
            "id": "100076747794030",
            "count": 0,
            "name": "Jako Mất Ngủ"
        },
        {
            "id": "100092162366896",
            "count": 0,
            "name": "Iyu Thơm"
        },
        {
            "id": "100045313671777",
            "count": 0,
            "name": "Ái Xuân"
        },
        {
            "id": "100094296957853",
            "count": 0,
            "name": "Eric Nè"
        },
        {
            "id": "100047832720086",
            "count": 0,
            "name": "ĐuOtpquên Ngườitrong Mộnglà Ai"
        },
        {
            "id": "61558759585711",
            "count": 0,
            "name": "Hanzo Lquid"
        },
        {
            "id": "61558167103810",
            "count": 0,
            "name": "Tuyet Nhi"
        },
        {
            "id": "100089263542479",
            "count": 0,
            "name": "Ánh Nguyệt"
        },
        {
            "id": "100091885795030",
            "count": 0,
            "name": "Dolores Nabokov"
        },
        {
            "id": "61559924222307",
            "count": 0,
            "name": "Kiều Vũ Quang"
        },
        {
            "id": "100022088556574",
            "count": 0,
            "name": "Ngô Thị Nguyên"
        },
        {
            "id": "61555802415021",
            "count": 0,
            "name": "Zin Dak"
        },
        {
            "id": "100072118997942",
            "count": 0,
            "name": "Nguyễn Thị Ngọc Thy"
        },
        {
            "id": "61551677327636",
            "count": 0,
            "name": "Ylinhh Aww"
        },
        {
            "id": "100084451148154",
            "count": 0,
            "name": "Thuy Linh"
        },
        {
            "id": "61555932106977",
            "count": 0,
            "name": "Ng Dkhanhh"
        },
        {
            "id": "61558980782920",
            "count": 0,
            "name": "Trần Hoàng Long'zz"
        },
        {
            "id": "100076986559695",
            "count": 0,
            "name": "Yến 's"
        },
        {
            "id": "100062402694808",
            "count": 0,
            "name": "Phuong Trình"
        },
        {
            "id": "61554868495444",
            "count": 0,
            "name": "Sườn Xào Chua Lè"
        },
        {
            "id": "61560526196531",
            "count": 0,
            "name": "Cáo Già Hazko"
        },
        {
            "id": "61557458320499",
            "count": 0,
            "name": "吕明"
        },
        {
            "id": "61561083304968",
            "count": 0,
            "name": "Ng Gia Linhh"
        },
        {
            "id": "100029609839915",
            "count": 0,
            "name": "Nguyễn Thị Mộng Tuyền"
        },
        {
            "id": "100080955501166",
            "count": 0,
            "name": "Vlakdislav Nguyen"
        },
        {
            "id": "61560272435082",
            "count": 0,
            "name": "Nguyett Anh"
        },
        {
            "id": "100088522154088",
            "count": 0,
            "name": "Ngọc Hà"
        },
        {
            "id": "61557646453984",
            "count": 0,
            "name": "Nhatlinhh"
        },
        {
            "id": "100063494506611",
            "count": 0,
            "name": "Dạ Minh"
        },
        {
            "id": "61555275488530",
            "count": 0,
            "name": "Lam Nhu メ"
        },
        {
            "id": "61559683718272",
            "count": 0,
            "name": "Tipi Owo"
        },
        {
            "id": "61559402953522",
            "count": 0,
            "name": "Amie Yutoki"
        },
        {
            "id": "61557543538603",
            "count": 0,
            "name": "Ken Yeuem"
        },
        {
            "id": "100090484572893",
            "count": 0,
            "name": "Croissant Vị Vani"
        },
        {
            "id": "61553785805211",
            "count": 0,
            "name": "Ngocc Lam"
        },
        {
            "id": "61557564551067",
            "count": 0,
            "name": "Trân Nhã"
        },
        {
            "id": "100074751587160",
            "count": 0,
            "name": "Tsukiyami Kenji"
        },
        {
            "id": "61556569884849",
            "count": 0,
            "name": "Uyên Nhã"
        },
        {
            "id": "61556541176393",
            "count": 0,
            "name": "Quynh Anh"
        },
        {
            "id": "100066564932411",
            "count": 0,
            "name": "Phương Nhi"
        },
        {
            "id": "100084606307564",
            "count": 0,
            "name": "Baoo Ngann"
        },
        {
            "id": "61560935327622",
            "count": 0,
            "name": "Diệp Lưu"
        },
        {
            "id": "100089195796584",
            "count": 0,
            "name": "Dũng Nguyễn"
        },
        {
            "id": "61560917451145",
            "count": 0,
            "name": "Nigwa Káaa"
        },
        {
            "id": "100091887548073",
            "count": 0,
            "name": "Ng's Ngocz Qnhii"
        },
        {
            "id": "100059415515587",
            "count": 0,
            "name": "Minh Tuan"
        },
        {
            "id": "100070262270937",
            "count": 0,
            "name": "Đào Như"
        },
        {
            "id": "61561027125365",
            "count": 0,
            "name": "Tao Là Dprii"
        },
        {
            "id": "100055154154050",
            "count": 0,
            "name": "Võ N-đăng"
        },
        {
            "id": "100067455634994",
            "count": 0,
            "name": "Королев Евгения"
        },
        {
            "id": "61550042293602",
            "count": 0,
            "name": "Trần Phuong Anh"
        },
        {
            "id": "61561510254962",
            "count": 0,
            "name": "Cha Mxh"
        },
        {
            "id": "61551991460052",
            "count": 0,
            "name": "Trúc Mã"
        }
    ],
    "time": 0,
    "last": {
        "time": 6,
        "day": [
            {
                "id": "61556886926538",
                "count": 0
            },
            {
                "id": "61558838883021",
                "count": 0
            },
            {
                "id": "100076747794030",
                "count": 0
            },
            {
                "id": "100092162366896",
                "count": 0
            },
            {
                "id": "100045313671777",
                "count": 0
            },
            {
                "id": "100094296957853",
                "count": 0
            },
            {
                "id": "100047832720086",
                "count": 0
            },
            {
                "id": "61558759585711",
                "count": 0
            },
            {
                "id": "61558167103810",
                "count": 0
            },
            {
                "id": "100089263542479",
                "count": 0
            },
            {
                "id": "100091885795030",
                "count": 0
            },
            {
                "id": "61559924222307",
                "count": 0
            },
            {
                "id": "100022088556574",
                "count": 0
            },
            {
                "id": "61555802415021",
                "count": 0
            },
            {
                "id": "100072118997942",
                "count": 0
            },
            {
                "id": "61551677327636",
                "count": 0
            },
            {
                "id": "100084451148154",
                "count": 0
            },
            {
                "id": "61555932106977",
                "count": 0
            },
            {
                "id": "61558980782920",
                "count": 0
            },
            {
                "id": "100076986559695",
                "count": 0
            },
            {
                "id": "100062402694808",
                "count": 0
            },
            {
                "id": "61554868495444",
                "count": 0
            },
            {
                "id": "61560526196531",
                "count": 0
            },
            {
                "id": "61557458320499",
                "count": 0
            },
            {
                "id": "61561083304968",
                "count": 0
            },
            {
                "id": "100029609839915",
                "count": 0
            },
            {
                "id": "100080955501166",
                "count": 0
            },
            {
                "id": "61560272435082",
                "count": 0
            },
            {
                "id": "100088522154088",
                "count": 0
            },
            {
                "id": "61557646453984",
                "count": 0
            },
            {
                "id": "100063494506611",
                "count": 0
            },
            {
                "id": "61555275488530",
                "count": 0
            },
            {
                "id": "61559683718272",
                "count": 0
            },
            {
                "id": "61559402953522",
                "count": 0
            },
            {
                "id": "61557543538603",
                "count": 0
            },
            {
                "id": "100090484572893",
                "count": 0
            },
            {
                "id": "61553785805211",
                "count": 0
            },
            {
                "id": "61557564551067",
                "count": 0
            },
            {
                "id": "100074751587160",
                "count": 0
            },
            {
                "id": "61556569884849",
                "count": 0
            },
            {
                "id": "61556541176393",
                "count": 0
            },
            {
                "id": "100066564932411",
                "count": 0
            },
            {
                "id": "100084606307564",
                "count": 0
            },
            {
                "id": "61560935327622",
                "count": 0
            },
            {
                "id": "100089195796584",
                "count": 0
            },
            {
                "id": "61560917451145",
                "count": 0
            },
            {
                "id": "100091887548073",
                "count": 0
            },
            {
                "id": "100059415515587",
                "count": 0
            },
            {
                "id": "100070262270937",
                "count": 0
            },
            {
                "id": "61561027125365",
                "count": 0
            },
            {
                "id": "100055154154050",
                "count": 0
            },
            {
                "id": "100067455634994",
                "count": 0
            },
            {
                "id": "61550042293602",
                "count": 0
            },
            {
                "id": "61561510254962",
                "count": 0
            },
            {
                "id": "61551991460052",
                "count": 0
            }
        ],
        "week": [
            {
                "id": "61556886926538",
                "count": 0
            },
            {
                "id": "61558838883021",
                "count": 0
            },
            {
                "id": "100076747794030",
                "count": 0
            },
            {
                "id": "100092162366896",
                "count": 0
            },
            {
                "id": "100045313671777",
                "count": 0
            },
            {
                "id": "100094296957853",
                "count": 0
            },
            {
                "id": "100047832720086",
                "count": 0
            },
            {
                "id": "61558759585711",
                "count": 0
            },
            {
                "id": "61558167103810",
                "count": 0
            },
            {
                "id": "100089263542479",
                "count": 0
            },
            {
                "id": "100091885795030",
                "count": 0
            },
            {
                "id": "61559924222307",
                "count": 0
            },
            {
                "id": "100022088556574",
                "count": 0
            },
            {
                "id": "61555802415021",
                "count": 0
            },
            {
                "id": "100072118997942",
                "count": 0
            },
            {
                "id": "61551677327636",
                "count": 0
            },
            {
                "id": "100084451148154",
                "count": 0
            },
            {
                "id": "61555932106977",
                "count": 0
            },
            {
                "id": "61558980782920",
                "count": 0
            },
            {
                "id": "100076986559695",
                "count": 0
            },
            {
                "id": "100062402694808",
                "count": 0
            },
            {
                "id": "61554868495444",
                "count": 0
            },
            {
                "id": "61560526196531",
                "count": 0
            },
            {
                "id": "61557458320499",
                "count": 0
            },
            {
                "id": "61561083304968",
                "count": 0
            },
            {
                "id": "100029609839915",
                "count": 0
            },
            {
                "id": "100080955501166",
                "count": 0
            },
            {
                "id": "61560272435082",
                "count": 0
            },
            {
                "id": "100088522154088",
                "count": 0
            },
            {
                "id": "61557646453984",
                "count": 0
            },
            {
                "id": "100063494506611",
                "count": 0
            },
            {
                "id": "61555275488530",
                "count": 0
            },
            {
                "id": "61559683718272",
                "count": 0
            },
            {
                "id": "61559402953522",
                "count": 0
            },
            {
                "id": "61557543538603",
                "count": 0
            },
            {
                "id": "100090484572893",
                "count": 0
            },
            {
                "id": "61553785805211",
                "count": 0
            },
            {
                "id": "61557564551067",
                "count": 0
            },
            {
                "id": "100074751587160",
                "count": 0
            },
            {
                "id": "61556569884849",
                "count": 0
            },
            {
                "id": "61556541176393",
                "count": 0
            },
            {
                "id": "100066564932411",
                "count": 0
            },
            {
                "id": "100084606307564",
                "count": 0
            },
            {
                "id": "61560935327622",
                "count": 0
            },
            {
                "id": "100089195796584",
                "count": 0
            },
            {
                "id": "61560917451145",
                "count": 0
            },
            {
                "id": "100091887548073",
                "count": 0
            },
            {
                "id": "100059415515587",
                "count": 0
            },
            {
                "id": "100070262270937",
                "count": 0
            },
            {
                "id": "61561027125365",
                "count": 0
            },
            {
                "id": "100055154154050",
                "count": 0
            },
            {
                "id": "100067455634994",
                "count": 0
            },
            {
                "id": "61550042293602",
                "count": 0
            },
            {
                "id": "61561510254962",
                "count": 0
            },
            {
                "id": "61551991460052",
                "count": 0
            }
        ]
    }
}