{
    "total": [
        {
            "id": "100079132448629",
            "count": 0
        },
        {
            "id": "100094006972864",
            "count": 0
        },
        {
            "id": "100073623571115",
            "count": 0
        },
        {
            "id": "61558658907368",
            "count": 0
        },
        {
            "id": "100053542083573",
            "count": 0
        },
        {
            "id": "61558107230572",
            "count": 0
        },
        {
            "id": "100074032503405",
            "count": 0
        },
        {
            "id": "61554735027856",
            "count": 0
        },
        {
            "id": "100091840270898",
            "count": 0
        },
        {
            "id": "61554891880641",
            "count": 0
        },
        {
            "id": "61550516648732",
            "count": 25
        },
        {
            "id": "61557789980689",
            "count": 0
        },
        {
            "id": "61554971972548",
            "count": 0
        },
        {
            "id": "100089879079030",
            "count": 0
        },
        {
            "id": "100088058215279",
            "count": 0
        },
        {
            "id": "61551876644346",
            "count": 0
        },
        {
            "id": "61550098605536",
            "count": 4
        },
        {
            "id": "100094185876634",
            "count": 0
        },
        {
            "id": "61559455583731",
            "count": 0
        },
        {
            "id": "100079155086318",
            "count": 0
        },
        {
            "id": "61557288126589",
            "count": 0
        },
        {
            "id": "61556521073390",
            "count": 0
        },
        {
            "id": "100086984672382",
            "count": 0
        },
        {
            "id": "61556177794858",
            "count": 0
        },
        {
            "id": "100086036762914",
            "count": 0
        },
        {
            "id": "100091160336544",
            "count": 0
        },
        {
            "id": "61557294960927",
            "count": 0
        },
        {
            "id": "61556692412784",
            "count": 0
        },
        {
            "id": "100077446394689",
            "count": 0
        },
        {
            "id": "61553144893702",
            "count": 0
        },
        {
            "id": "61557252974749",
            "count": 0
        },
        {
            "id": "100050287896116",
            "count": 0
        },
        {
            "id": "100087190938185",
            "count": 0
        },
        {
            "id": "100055944649291",
            "count": 0
        },
        {
            "id": "100071251879614",
            "count": 0
        },
        {
            "id": "61557405557552",
            "count": 1
        },
        {
            "id": "61553586700599",
            "count": 0
        },
        {
            "id": "61554699172420",
            "count": 0
        },
        {
            "id": "61555770071353",
            "count": 0
        },
        {
            "id": "100079234315183",
            "count": 0
        },
        {
            "id": "100071208644984",
            "count": 3
        },
        {
            "id": "100087884771206",
            "count": 0
        },
        {
            "id": "100091357779214",
            "count": 2
        },
        {
            "id": "100084455526937",
            "count": 0
        },
        {
            "id": "100091103288999",
            "count": 0
        },
        {
            "id": "100027677536369",
            "count": 16
        },
        {
            "id": "100076389371363",
            "count": 0
        },
        {
            "id": "61554875622433",
            "count": 0
        },
        {
            "id": "61559953546936",
            "count": 0
        },
        {
            "id": "100088127163780",
            "count": 0
        },
        {
            "id": "100079722127350",
            "count": 0
        },
        {
            "id": "100095316475318",
            "count": 5
        },
        {
            "id": "61560465518058",
            "count": 0
        },
        {
            "id": "100089145891021",
            "count": 2
        },
        {
            "id": "100039361512946",
            "count": 0
        },
        {
            "id": "100049193643183",
            "count": 32
        },
        {
            "id": "61552543256538",
            "count": 0
        },
        {
            "id": "61554732772416",
            "count": 182
        },
        {
            "id": "100053419878673",
            "count": 0
        },
        {
            "id": "100073173380398",
            "count": 0
        },
        {
            "id": "61551835215042",
            "count": 67
        },
        {
            "id": "61557243833508",
            "count": 0
        },
        {
            "id": "61552597790250",
            "count": 0
        },
        {
            "id": "100052668398850",
            "count": 10
        },
        {
            "id": "100083946362419",
            "count": 0
        },
        {
            "id": "61554751779393",
            "count": 0
        },
        {
            "id": "100046727511219",
            "count": 0
        },
        {
            "id": "100041079390776",
            "count": 6
        },
        {
            "id": "100070009642150",
            "count": 0
        },
        {
            "id": "61554664329196",
            "count": 0
        },
        {
            "id": "61560430062304",
            "count": 0
        },
        {
            "id": "61553792534629",
            "count": 1
        },
        {
            "id": "61559694170782",
            "count": 0
        },
        {
            "id": "100078930363394",
            "count": 14
        },
        {
            "id": "61561373969644",
            "count": 0
        },
        {
            "id": "61551866410679",
            "count": 40
        },
        {
            "id": "61560459479211",
            "count": 0
        },
        {
            "id": "100092164964555",
            "count": 0
        },
        {
            "id": "61556325563717",
            "count": 3
        },
        {
            "id": "61558621154028",
            "count": 2
        },
        {
            "id": "100089667847915",
            "count": 204
        },
        {
            "id": "100070978874662",
            "count": 10
        },
        {
            "id": "61558530423601",
            "count": 0
        },
        {
            "id": "61556886926538",
            "count": 0
        },
        {
            "id": "61560752645570",
            "count": 0
        },
        {
            "id": "100055154154050",
            "count": 8
        },
        {
            "id": "61561482763717",
            "count": 52
        },
        {
            "id": "100090652847542",
            "count": 19
        },
        {
            "id": "61560858584297",
            "count": 14
        },
        {
            "id": "61560395143700",
            "count": 7
        },
        {
            "id": "100054715670750",
            "count": 1
        },
        {
            "id": "61550188172293",
            "count": 10
        },
        {
            "id": "100000860148761",
            "count": 2
        },
        {
            "id": "61560659728873",
            "count": 0
        },
        {
            "id": "61560587615424",
            "count": 6
        },
        {
            "id": "100066102592699",
            "count": 0
        },
        {
            "id": "100081742705700",
            "count": 0
        },
        {
            "id": "61562530282223",
            "count": 0
        },
        {
            "id": "61561510254962",
            "count": 4
        },
        {
            "id": "100080916333053",
            "count": 0
        },
        {
            "id": "100085515350448",
            "count": 1
        }
    ],
    "week": [
        {
            "id": "100079132448629",
            "count": 0
        },
        {
            "id": "100094006972864",
            "count": 0
        },
        {
            "id": "100073623571115",
            "count": 0
        },
        {
            "id": "61558658907368",
            "count": 0
        },
        {
            "id": "100053542083573",
            "count": 0
        },
        {
            "id": "61558107230572",
            "count": 0
        },
        {
            "id": "100074032503405",
            "count": 0
        },
        {
            "id": "61554735027856",
            "count": 0
        },
        {
            "id": "100091840270898",
            "count": 0
        },
        {
            "id": "61554891880641",
            "count": 0
        },
        {
            "id": "61550516648732",
            "count": 25
        },
        {
            "id": "61557789980689",
            "count": 0
        },
        {
            "id": "61554971972548",
            "count": 0
        },
        {
            "id": "100089879079030",
            "count": 0
        },
        {
            "id": "100088058215279",
            "count": 0
        },
        {
            "id": "61551876644346",
            "count": 0
        },
        {
            "id": "61550098605536",
            "count": 4
        },
        {
            "id": "100094185876634",
            "count": 0
        },
        {
            "id": "61559455583731",
            "count": 0
        },
        {
            "id": "100079155086318",
            "count": 0
        },
        {
            "id": "61557288126589",
            "count": 0
        },
        {
            "id": "61556521073390",
            "count": 0
        },
        {
            "id": "100086984672382",
            "count": 0
        },
        {
            "id": "61556177794858",
            "count": 0
        },
        {
            "id": "100086036762914",
            "count": 0
        },
        {
            "id": "100091160336544",
            "count": 0
        },
        {
            "id": "61557294960927",
            "count": 0
        },
        {
            "id": "61556692412784",
            "count": 0
        },
        {
            "id": "100077446394689",
            "count": 0
        },
        {
            "id": "61553144893702",
            "count": 0
        },
        {
            "id": "61557252974749",
            "count": 0
        },
        {
            "id": "100050287896116",
            "count": 0
        },
        {
            "id": "100087190938185",
            "count": 0
        },
        {
            "id": "100055944649291",
            "count": 0
        },
        {
            "id": "100071251879614",
            "count": 0
        },
        {
            "id": "61557405557552",
            "count": 1
        },
        {
            "id": "61553586700599",
            "count": 0
        },
        {
            "id": "61554699172420",
            "count": 0
        },
        {
            "id": "61555770071353",
            "count": 0
        },
        {
            "id": "100079234315183",
            "count": 0
        },
        {
            "id": "100071208644984",
            "count": 3
        },
        {
            "id": "100087884771206",
            "count": 0
        },
        {
            "id": "100091357779214",
            "count": 2
        },
        {
            "id": "100084455526937",
            "count": 0
        },
        {
            "id": "100091103288999",
            "count": 0
        },
        {
            "id": "100027677536369",
            "count": 16
        },
        {
            "id": "100076389371363",
            "count": 0
        },
        {
            "id": "61554875622433",
            "count": 0
        },
        {
            "id": "61559953546936",
            "count": 0
        },
        {
            "id": "100088127163780",
            "count": 0
        },
        {
            "id": "100079722127350",
            "count": 0
        },
        {
            "id": "100095316475318",
            "count": 5
        },
        {
            "id": "61560465518058",
            "count": 0
        },
        {
            "id": "100089145891021",
            "count": 2
        },
        {
            "id": "100039361512946",
            "count": 0
        },
        {
            "id": "100049193643183",
            "count": 32
        },
        {
            "id": "61552543256538",
            "count": 0
        },
        {
            "id": "61554732772416",
            "count": 182
        },
        {
            "id": "100053419878673",
            "count": 0
        },
        {
            "id": "100073173380398",
            "count": 0
        },
        {
            "id": "61551835215042",
            "count": 67
        },
        {
            "id": "61557243833508",
            "count": 0
        },
        {
            "id": "61552597790250",
            "count": 0
        },
        {
            "id": "100052668398850",
            "count": 10
        },
        {
            "id": "100083946362419",
            "count": 0
        },
        {
            "id": "61554751779393",
            "count": 0
        },
        {
            "id": "100046727511219",
            "count": 0
        },
        {
            "id": "100041079390776",
            "count": 6
        },
        {
            "id": "100070009642150",
            "count": 0
        },
        {
            "id": "61554664329196",
            "count": 0
        },
        {
            "id": "61560430062304",
            "count": 0
        },
        {
            "id": "61553792534629",
            "count": 1
        },
        {
            "id": "61559694170782",
            "count": 0
        },
        {
            "id": "100078930363394",
            "count": 14
        },
        {
            "id": "61561373969644",
            "count": 0
        },
        {
            "id": "61551866410679",
            "count": 40
        },
        {
            "id": "61560459479211",
            "count": 0
        },
        {
            "id": "100092164964555",
            "count": 0
        },
        {
            "id": "61556325563717",
            "count": 3
        },
        {
            "id": "61558621154028",
            "count": 2
        },
        {
            "id": "100089667847915",
            "count": 204
        },
        {
            "id": "100070978874662",
            "count": 10
        },
        {
            "id": "61558530423601",
            "count": 0
        },
        {
            "id": "61556886926538",
            "count": 0
        },
        {
            "id": "61560752645570",
            "count": 0
        },
        {
            "id": "100055154154050",
            "count": 8
        },
        {
            "id": "61561482763717",
            "count": 52
        },
        {
            "id": "100090652847542",
            "count": 19
        },
        {
            "id": "61560858584297",
            "count": 14
        },
        {
            "id": "61560395143700",
            "count": 7
        },
        {
            "id": "100054715670750",
            "count": 1
        },
        {
            "id": "61550188172293",
            "count": 10
        },
        {
            "id": "100000860148761",
            "count": 2
        },
        {
            "id": "61560659728873",
            "count": 0
        },
        {
            "id": "61560587615424",
            "count": 6
        },
        {
            "id": "100066102592699",
            "count": 0
        },
        {
            "id": "100081742705700",
            "count": 0
        },
        {
            "id": "61562530282223",
            "count": 0
        },
        {
            "id": "61561510254962",
            "count": 4
        },
        {
            "id": "100080916333053",
            "count": 0
        },
        {
            "id": "100085515350448",
            "count": 1
        }
    ],
    "day": [
        {
            "id": "100079132448629",
            "count": 0
        },
        {
            "id": "100094006972864",
            "count": 0
        },
        {
            "id": "100073623571115",
            "count": 0
        },
        {
            "id": "61558658907368",
            "count": 0
        },
        {
            "id": "100053542083573",
            "count": 0
        },
        {
            "id": "61558107230572",
            "count": 0
        },
        {
            "id": "100074032503405",
            "count": 0
        },
        {
            "id": "61554735027856",
            "count": 0
        },
        {
            "id": "100091840270898",
            "count": 0
        },
        {
            "id": "61554891880641",
            "count": 0
        },
        {
            "id": "61550516648732",
            "count": 25
        },
        {
            "id": "61557789980689",
            "count": 0
        },
        {
            "id": "61554971972548",
            "count": 0
        },
        {
            "id": "100089879079030",
            "count": 0
        },
        {
            "id": "100088058215279",
            "count": 0
        },
        {
            "id": "61551876644346",
            "count": 0
        },
        {
            "id": "61550098605536",
            "count": 4
        },
        {
            "id": "100094185876634",
            "count": 0
        },
        {
            "id": "61559455583731",
            "count": 0
        },
        {
            "id": "100079155086318",
            "count": 0
        },
        {
            "id": "61557288126589",
            "count": 0
        },
        {
            "id": "61556521073390",
            "count": 0
        },
        {
            "id": "100086984672382",
            "count": 0
        },
        {
            "id": "61556177794858",
            "count": 0
        },
        {
            "id": "100086036762914",
            "count": 0
        },
        {
            "id": "100091160336544",
            "count": 0
        },
        {
            "id": "61557294960927",
            "count": 0
        },
        {
            "id": "61556692412784",
            "count": 0
        },
        {
            "id": "100077446394689",
            "count": 0
        },
        {
            "id": "61553144893702",
            "count": 0
        },
        {
            "id": "61557252974749",
            "count": 0
        },
        {
            "id": "100050287896116",
            "count": 0
        },
        {
            "id": "100087190938185",
            "count": 0
        },
        {
            "id": "100055944649291",
            "count": 0
        },
        {
            "id": "100071251879614",
            "count": 0
        },
        {
            "id": "61557405557552",
            "count": 1
        },
        {
            "id": "61553586700599",
            "count": 0
        },
        {
            "id": "61554699172420",
            "count": 0
        },
        {
            "id": "61555770071353",
            "count": 0
        },
        {
            "id": "100079234315183",
            "count": 0
        },
        {
            "id": "100071208644984",
            "count": 3
        },
        {
            "id": "100087884771206",
            "count": 0
        },
        {
            "id": "100091357779214",
            "count": 2
        },
        {
            "id": "100084455526937",
            "count": 0
        },
        {
            "id": "100091103288999",
            "count": 0
        },
        {
            "id": "100027677536369",
            "count": 16
        },
        {
            "id": "100076389371363",
            "count": 0
        },
        {
            "id": "61554875622433",
            "count": 0
        },
        {
            "id": "61559953546936",
            "count": 0
        },
        {
            "id": "100088127163780",
            "count": 0
        },
        {
            "id": "100079722127350",
            "count": 0
        },
        {
            "id": "100095316475318",
            "count": 5
        },
        {
            "id": "61560465518058",
            "count": 0
        },
        {
            "id": "100089145891021",
            "count": 2
        },
        {
            "id": "100039361512946",
            "count": 0
        },
        {
            "id": "100049193643183",
            "count": 32
        },
        {
            "id": "61552543256538",
            "count": 0
        },
        {
            "id": "61554732772416",
            "count": 182
        },
        {
            "id": "100053419878673",
            "count": 0
        },
        {
            "id": "100073173380398",
            "count": 0
        },
        {
            "id": "61551835215042",
            "count": 67
        },
        {
            "id": "61557243833508",
            "count": 0
        },
        {
            "id": "61552597790250",
            "count": 0
        },
        {
            "id": "100052668398850",
            "count": 10
        },
        {
            "id": "100083946362419",
            "count": 0
        },
        {
            "id": "61554751779393",
            "count": 0
        },
        {
            "id": "100046727511219",
            "count": 0
        },
        {
            "id": "100041079390776",
            "count": 6
        },
        {
            "id": "100070009642150",
            "count": 0
        },
        {
            "id": "61554664329196",
            "count": 0
        },
        {
            "id": "61560430062304",
            "count": 0
        },
        {
            "id": "61553792534629",
            "count": 1
        },
        {
            "id": "61559694170782",
            "count": 0
        },
        {
            "id": "100078930363394",
            "count": 14
        },
        {
            "id": "61561373969644",
            "count": 0
        },
        {
            "id": "61551866410679",
            "count": 40
        },
        {
            "id": "61560459479211",
            "count": 0
        },
        {
            "id": "100092164964555",
            "count": 0
        },
        {
            "id": "61556325563717",
            "count": 3
        },
        {
            "id": "61558621154028",
            "count": 2
        },
        {
            "id": "100089667847915",
            "count": 204
        },
        {
            "id": "100070978874662",
            "count": 10
        },
        {
            "id": "61558530423601",
            "count": 0
        },
        {
            "id": "61556886926538",
            "count": 0
        },
        {
            "id": "61560752645570",
            "count": 0
        },
        {
            "id": "100055154154050",
            "count": 8
        },
        {
            "id": "61561482763717",
            "count": 52
        },
        {
            "id": "100090652847542",
            "count": 19
        },
        {
            "id": "61560858584297",
            "count": 14
        },
        {
            "id": "61560395143700",
            "count": 7
        },
        {
            "id": "100054715670750",
            "count": 1
        },
        {
            "id": "61550188172293",
            "count": 10
        },
        {
            "id": "100000860148761",
            "count": 2
        },
        {
            "id": "61560659728873",
            "count": 0
        },
        {
            "id": "61560587615424",
            "count": 6
        },
        {
            "id": "100066102592699",
            "count": 0
        },
        {
            "id": "100081742705700",
            "count": 0
        },
        {
            "id": "61562530282223",
            "count": 0
        },
        {
            "id": "61561510254962",
            "count": 4
        },
        {
            "id": "100080916333053",
            "count": 0
        },
        {
            "id": "100085515350448",
            "count": 1
        }
    ],
    "time": 0,
    "last": {
        "time": 1,
        "day": [
            {
                "id": "100079132448629",
                "count": 0
            },
            {
                "id": "100094006972864",
                "count": 0
            },
            {
                "id": "100073623571115",
                "count": 0
            },
            {
                "id": "61558658907368",
                "count": 0
            },
            {
                "id": "100053542083573",
                "count": 0
            },
            {
                "id": "61558107230572",
                "count": 0
            },
            {
                "id": "100074032503405",
                "count": 0
            },
            {
                "id": "61554735027856",
                "count": 0
            },
            {
                "id": "100091840270898",
                "count": 0
            },
            {
                "id": "61554891880641",
                "count": 0
            },
            {
                "id": "61550516648732",
                "count": 0
            },
            {
                "id": "61557789980689",
                "count": 0
            },
            {
                "id": "61554971972548",
                "count": 0
            },
            {
                "id": "100060802511791",
                "count": 0
            },
            {
                "id": "100089879079030",
                "count": 0
            },
            {
                "id": "100088058215279",
                "count": 0
            },
            {
                "id": "61551876644346",
                "count": 0
            },
            {
                "id": "61550098605536",
                "count": 0
            },
            {
                "id": "100094185876634",
                "count": 0
            },
            {
                "id": "61559455583731",
                "count": 0
            },
            {
                "id": "100079155086318",
                "count": 0
            },
            {
                "id": "61557288126589",
                "count": 0
            },
            {
                "id": "61556521073390",
                "count": 0
            },
            {
                "id": "100086984672382",
                "count": 0
            },
            {
                "id": "61556177794858",
                "count": 0
            },
            {
                "id": "100086036762914",
                "count": 0
            },
            {
                "id": "100091160336544",
                "count": 0
            },
            {
                "id": "61557294960927",
                "count": 0
            },
            {
                "id": "61556692412784",
                "count": 0
            },
            {
                "id": "100077446394689",
                "count": 0
            },
            {
                "id": "61553144893702",
                "count": 0
            },
            {
                "id": "61557252974749",
                "count": 0
            },
            {
                "id": "100050287896116",
                "count": 0
            },
            {
                "id": "100087190938185",
                "count": 0
            },
            {
                "id": "100055944649291",
                "count": 0
            },
            {
                "id": "61557152201272",
                "count": 0
            },
            {
                "id": "100071251879614",
                "count": 0
            },
            {
                "id": "61557405557552",
                "count": 0
            },
            {
                "id": "61553586700599",
                "count": 0
            },
            {
                "id": "61554699172420",
                "count": 0
            },
            {
                "id": "61555770071353",
                "count": 0
            },
            {
                "id": "100079234315183",
                "count": 0
            },
            {
                "id": "100071208644984",
                "count": 0
            },
            {
                "id": "100087884771206",
                "count": 0
            },
            {
                "id": "100091357779214",
                "count": 0
            },
            {
                "id": "100084455526937",
                "count": 0
            },
            {
                "id": "100091103288999",
                "count": 0
            },
            {
                "id": "100027677536369",
                "count": 0
            },
            {
                "id": "100076389371363",
                "count": 0
            },
            {
                "id": "61554875622433",
                "count": 0
            },
            {
                "id": "61559953546936",
                "count": 0
            },
            {
                "id": "100088127163780",
                "count": 0
            },
            {
                "id": "100079722127350",
                "count": 0
            },
            {
                "id": "61559156687615",
                "count": 0
            },
            {
                "id": "100095316475318",
                "count": 0
            },
            {
                "id": "61560465518058",
                "count": 0
            },
            {
                "id": "100089145891021",
                "count": 0
            },
            {
                "id": "100039361512946",
                "count": 0
            },
            {
                "id": "100049193643183",
                "count": 0
            },
            {
                "id": "61552543256538",
                "count": 0
            },
            {
                "id": "61554732772416",
                "count": 0
            },
            {
                "id": "100053419878673",
                "count": 0
            },
            {
                "id": "100073173380398",
                "count": 0
            },
            {
                "id": "61551835215042",
                "count": 0
            },
            {
                "id": "61557243833508",
                "count": 0
            },
            {
                "id": "61552597790250",
                "count": 0
            },
            {
                "id": "100052668398850",
                "count": 0
            },
            {
                "id": "100083946362419",
                "count": 0
            },
            {
                "id": "61554751779393",
                "count": 0
            },
            {
                "id": "100046727511219",
                "count": 0
            },
            {
                "id": "100041079390776",
                "count": 0
            },
            {
                "id": "100070009642150",
                "count": 0
            },
            {
                "id": "61554664329196",
                "count": 0
            },
            {
                "id": "61560430062304",
                "count": 0
            },
            {
                "id": "61553792534629",
                "count": 0
            },
            {
                "id": "61559694170782",
                "count": 0
            },
            {
                "id": "100078930363394",
                "count": 0
            },
            {
                "id": "61561373969644",
                "count": 0
            },
            {
                "id": "61551866410679",
                "count": 0
            },
            {
                "id": "61560459479211",
                "count": 0
            },
            {
                "id": "100092164964555",
                "count": 0
            },
            {
                "id": "61556325563717",
                "count": 0
            },
            {
                "id": "61558621154028",
                "count": 0
            },
            {
                "id": "61559602534890",
                "count": 0
            },
            {
                "id": "100089667847915",
                "count": 0
            },
            {
                "id": "100070978874662",
                "count": 0
            },
            {
                "id": "61558530423601",
                "count": 0
            },
            {
                "id": "61556886926538",
                "count": 0
            },
            {
                "id": "61560752645570",
                "count": 0
            },
            {
                "id": "100055154154050",
                "count": 0
            },
            {
                "id": "61561482763717",
                "count": 0
            },
            {
                "id": "100090652847542",
                "count": 0
            },
            {
                "id": "61560858584297",
                "count": 0
            },
            {
                "id": "61560395143700",
                "count": 0
            },
            {
                "id": "100054715670750",
                "count": 0
            },
            {
                "id": "61550188172293",
                "count": 0
            },
            {
                "id": "100085049701568",
                "count": 0
            },
            {
                "id": "100000860148761",
                "count": 0
            },
            {
                "id": "61560659728873",
                "count": 0
            },
            {
                "id": "61560587615424",
                "count": 0
            },
            {
                "id": "100066102592699",
                "count": 0
            },
            {
                "id": "100081742705700",
                "count": 0
            },
            {
                "id": "61562530282223",
                "count": 0
            },
            {
                "id": "61561510254962",
                "count": 0
            },
            {
                "id": "100080916333053",
                "count": 0
            },
            {
                "id": "100085515350448",
                "count": 0
            }
        ],
        "week": [
            {
                "id": "100079132448629",
                "count": 0
            },
            {
                "id": "100094006972864",
                "count": 0
            },
            {
                "id": "100073623571115",
                "count": 0
            },
            {
                "id": "61558658907368",
                "count": 0
            },
            {
                "id": "100053542083573",
                "count": 0
            },
            {
                "id": "61558107230572",
                "count": 0
            },
            {
                "id": "100074032503405",
                "count": 0
            },
            {
                "id": "61554735027856",
                "count": 0
            },
            {
                "id": "100091840270898",
                "count": 0
            },
            {
                "id": "61554891880641",
                "count": 0
            },
            {
                "id": "61550516648732",
                "count": 0
            },
            {
                "id": "61557789980689",
                "count": 0
            },
            {
                "id": "61554971972548",
                "count": 0
            },
            {
                "id": "100060802511791",
                "count": 0
            },
            {
                "id": "100089879079030",
                "count": 0
            },
            {
                "id": "100088058215279",
                "count": 0
            },
            {
                "id": "61551876644346",
                "count": 0
            },
            {
                "id": "61550098605536",
                "count": 0
            },
            {
                "id": "100094185876634",
                "count": 0
            },
            {
                "id": "61559455583731",
                "count": 0
            },
            {
                "id": "100079155086318",
                "count": 0
            },
            {
                "id": "61557288126589",
                "count": 0
            },
            {
                "id": "61556521073390",
                "count": 0
            },
            {
                "id": "100086984672382",
                "count": 0
            },
            {
                "id": "61556177794858",
                "count": 0
            },
            {
                "id": "100086036762914",
                "count": 0
            },
            {
                "id": "100091160336544",
                "count": 0
            },
            {
                "id": "61557294960927",
                "count": 0
            },
            {
                "id": "61556692412784",
                "count": 0
            },
            {
                "id": "100077446394689",
                "count": 0
            },
            {
                "id": "61553144893702",
                "count": 0
            },
            {
                "id": "61557252974749",
                "count": 0
            },
            {
                "id": "100050287896116",
                "count": 0
            },
            {
                "id": "100087190938185",
                "count": 0
            },
            {
                "id": "100055944649291",
                "count": 0
            },
            {
                "id": "61557152201272",
                "count": 0
            },
            {
                "id": "100071251879614",
                "count": 0
            },
            {
                "id": "61557405557552",
                "count": 0
            },
            {
                "id": "61553586700599",
                "count": 0
            },
            {
                "id": "61554699172420",
                "count": 0
            },
            {
                "id": "61555770071353",
                "count": 0
            },
            {
                "id": "100079234315183",
                "count": 0
            },
            {
                "id": "100071208644984",
                "count": 0
            },
            {
                "id": "100087884771206",
                "count": 0
            },
            {
                "id": "100091357779214",
                "count": 0
            },
            {
                "id": "100084455526937",
                "count": 0
            },
            {
                "id": "100091103288999",
                "count": 0
            },
            {
                "id": "100027677536369",
                "count": 0
            },
            {
                "id": "100076389371363",
                "count": 0
            },
            {
                "id": "61554875622433",
                "count": 0
            },
            {
                "id": "61559953546936",
                "count": 0
            },
            {
                "id": "100088127163780",
                "count": 0
            },
            {
                "id": "100079722127350",
                "count": 0
            },
            {
                "id": "61559156687615",
                "count": 0
            },
            {
                "id": "100095316475318",
                "count": 0
            },
            {
                "id": "61560465518058",
                "count": 0
            },
            {
                "id": "100089145891021",
                "count": 0
            },
            {
                "id": "100039361512946",
                "count": 0
            },
            {
                "id": "100049193643183",
                "count": 0
            },
            {
                "id": "61552543256538",
                "count": 0
            },
            {
                "id": "61554732772416",
                "count": 0
            },
            {
                "id": "100053419878673",
                "count": 0
            },
            {
                "id": "100073173380398",
                "count": 0
            },
            {
                "id": "61551835215042",
                "count": 0
            },
            {
                "id": "61557243833508",
                "count": 0
            },
            {
                "id": "61552597790250",
                "count": 0
            },
            {
                "id": "100052668398850",
                "count": 0
            },
            {
                "id": "100083946362419",
                "count": 0
            },
            {
                "id": "61554751779393",
                "count": 0
            },
            {
                "id": "100046727511219",
                "count": 0
            },
            {
                "id": "100041079390776",
                "count": 0
            },
            {
                "id": "100070009642150",
                "count": 0
            },
            {
                "id": "61554664329196",
                "count": 0
            },
            {
                "id": "61560430062304",
                "count": 0
            },
            {
                "id": "61553792534629",
                "count": 0
            },
            {
                "id": "61559694170782",
                "count": 0
            },
            {
                "id": "100078930363394",
                "count": 0
            },
            {
                "id": "61561373969644",
                "count": 0
            },
            {
                "id": "61551866410679",
                "count": 0
            },
            {
                "id": "61560459479211",
                "count": 0
            },
            {
                "id": "100092164964555",
                "count": 0
            },
            {
                "id": "61556325563717",
                "count": 0
            },
            {
                "id": "61558621154028",
                "count": 0
            },
            {
                "id": "61559602534890",
                "count": 0
            },
            {
                "id": "100089667847915",
                "count": 0
            },
            {
                "id": "100070978874662",
                "count": 0
            },
            {
                "id": "61558530423601",
                "count": 0
            },
            {
                "id": "61556886926538",
                "count": 0
            },
            {
                "id": "61560752645570",
                "count": 0
            },
            {
                "id": "100055154154050",
                "count": 0
            },
            {
                "id": "61561482763717",
                "count": 0
            },
            {
                "id": "100090652847542",
                "count": 0
            },
            {
                "id": "61560858584297",
                "count": 0
            },
            {
                "id": "61560395143700",
                "count": 0
            },
            {
                "id": "100054715670750",
                "count": 0
            },
            {
                "id": "61550188172293",
                "count": 0
            },
            {
                "id": "100085049701568",
                "count": 0
            },
            {
                "id": "100000860148761",
                "count": 0
            },
            {
                "id": "61560659728873",
                "count": 0
            },
            {
                "id": "61560587615424",
                "count": 0
            },
            {
                "id": "100066102592699",
                "count": 0
            },
            {
                "id": "100081742705700",
                "count": 0
            },
            {
                "id": "61562530282223",
                "count": 0
            },
            {
                "id": "61561510254962",
                "count": 0
            },
            {
                "id": "100080916333053",
                "count": 0
            },
            {
                "id": "100085515350448",
                "count": 0
            }
        ]
    }
}